Metadata-Version: 2.4
Name: spheresmooth
Version: 0.1.1
Summary: Geometry-aware spline smoothing and geodesic modeling for spherical data in Python
Author-email: Se-Young Lee <sudang0404@gmail.com>, Kwan-Young Bak <kybak@sungshin.ac.kr>
Maintainer-email: Se-Young Lee <sudang0404@gmail.com>
License-Expression: GPL-3.0-or-later
Project-URL: Homepage, https://github.com/seyoung-230/spheresmooth-python
Requires-Python: >=3.9
Requires-Dist: numpy>=1.24
Requires-Dist: pandas>=1.5
Provides-Extra: viz
Requires-Dist: matplotlib>=3.7; extra == "viz"
Requires-Dist: geopandas>=0.13; extra == "viz"
